{
    "$schema": "https://raw.githubusercontent.com/lukesampson/scoop/master/schema.json",
    "version": "1.02.000",
    "description": "Personal post-install customization bundle (member of the MarkMichaelis* run-last family). Pins OneDrive sync roots under a single parent, applies tenant-redirection policy, and rewrites KFM bindings to follow the canonical Work account. Runs AFTER all install bundles; reshapes state rather than installing software.",
    "url": [
        "https://raw.githubusercontent.com/MarkMichaelis/ScoopBucket/master/bucket/MarkMichaelisOneDriveConfiguration.ps1"
    ],
    "installer": {
        "script": "& \"$dir\\MarkMichaelisOneDriveConfiguration.ps1\""
    }
}
